llama_index/readers/gitlab/__init__.py
llama_index/readers/gitlab/issues/__init__.py
llama_index/readers/gitlab/issues/base.py
llama_index/readers/gitlab/repository/__init__.py
llama_index/readers/gitlab/repository/base.py
llama_index_readers_gitlab-0.5.1.dist-info/METADATA
llama_index_readers_gitlab-0.5.1.dist-info/WHEEL
llama_index_readers_gitlab-0.5.1.dist-info/licenses/LICENSE
llama_index_readers_gitlab-0.5.1.dist-info/RECORD
