Metadata-Version: 2.4
Name: llama-index-readers-gitlab
Version: 0.5.1
Summary: llama-index readers gitlab integration
Author-email: Jiacheng Zhang <jiachengzz@outlook.com>
Maintainer: jiachengzhang1
License-Expression: MIT
License-File: LICENSE
Requires-Python: <4.0,>=3.9
Requires-Dist: llama-index-core<0.15,>=0.13.0
Requires-Dist: python-gitlab<5,>=4.8.0
